setup.py
untrusted_process/__init__.py
untrusted_process/core.py
untrusted_process/setup.py
untrusted_process.egg-info/PKG-INFO
untrusted_process.egg-info/SOURCES.txt
untrusted_process.egg-info/dependency_links.txt
untrusted_process.egg-info/requires.txt
untrusted_process.egg-info/top_level.txt