Metadata-Version: 2.1
Name: untrusted-process
Version: 0.2
Summary: A package to analyze and visualize untrusted processes using osquery.
Home-page: https://github.com/your_username/untrusted_process
Author: Ahsan Ali
Author-email: misterj503@gmail.com
Classifier: License :: OSI Approved :: MIT License
Classifier: Programming Language :: Python :: 3
Classifier: Programming Language :: Python :: 3.6
Classifier: Programming Language :: Python :: 3.7
Classifier: Programming Language :: Python :: 3.8
Requires-Python: >=3.6
